billing_service/__init__.py
billing_service/asgi.py
billing_service/settings.py
billing_service/urls.py
billing_service/wsgi.py
uzcloud_billing/__init__.py
uzcloud_billing/admin.py
uzcloud_billing/apps.py
uzcloud_billing/choices.py
uzcloud_billing/decorators.py
uzcloud_billing/services.py
uzcloud_billing/signals.py
uzcloud_billing/urls.py
uzcloud_billing/utils.py
uzcloud_billing/api/__init__.py
uzcloud_billing/api/permissions.py
uzcloud_billing/api/serializers.py
uzcloud_billing/api/views.py
uzcloud_billing/management/__init__.py
uzcloud_billing/management/commands/__init__.py
uzcloud_billing/management/commands/create_billing_accounts.py
uzcloud_billing/migrations/0001_initial.py
uzcloud_billing/migrations/0002_billingaccount_balance.py
uzcloud_billing/migrations/0003_billingaccount_account_type_and_more.py
uzcloud_billing/migrations/0004_alter_billingaccount_user.py
uzcloud_billing/migrations/0005_alter_billingaccount_balance.py
uzcloud_billing/migrations/0006_billingaccount_created_at_billingaccount_updated_at.py
uzcloud_billing/migrations/__init__.py
uzcloud_billing/models/__init__.py
uzcloud_billing/models/billing.py
uzcloud_billing/models/manager.py
uzcloud_billing/models/mixin.py
uzcloud_billing-0.2.22.dist-info/licenses/LICENSE
uzcloud_billing-0.2.22.dist-info/METADATA
uzcloud_billing-0.2.22.dist-info/WHEEL
uzcloud_billing-0.2.22.dist-info/top_level.txt
uzcloud_billing-0.2.22.dist-info/RECORD
