Metadata-Version: 2.4
Name: uzcloud-billing
Version: 0.2.22
Summary: Uzcloud Billing
Home-page: https://arabboy3332@bitbucket.org/arabboy3332/uzcloud_billing.git
Author: Arabboy Mamadaliev
Author-email: mr.arabboy@gmail.com
License: MIT
Keywords: uzcloud,billing
Classifier: Environment :: Web Environment
Classifier: Framework :: Django
Classifier: Framework :: Django :: 4.0
Classifier: Intended Audience :: Developers
Classifier: License :: OSI Approved :: MIT License
Classifier: Operating System :: OS Independent
Classifier: Programming Language :: Python :: 3.9
Classifier: Programming Language :: Python :: 3.10
Classifier: Topic :: Software Development :: Libraries :: Python Modules
License-File: LICENSE
Requires-Dist: requests
Requires-Dist: PyJWT
Requires-Dist: djangorestframework
Dynamic: license-file
Dynamic: requires-dist
